langchain_kaburi/__init__.py
langchain_kaburi/math.py
langchain_kaburi/builders/__init__.py
langchain_kaburi/builders/image_message_builder.py
langchain_kaburi-0.0.8.dist-info/METADATA
langchain_kaburi-0.0.8.dist-info/WHEEL
langchain_kaburi-0.0.8.dist-info/top_level.txt
langchain_kaburi-0.0.8.dist-info/RECORD
